{
  "Polylines": [],
  "Polylines2d": [],
  "Lines": [],
  "Arcs": [
    {
      "Center": {
        "X": 0.19894053612006246,
        "Y": 1.3750000000006821,
        "Z": 0.0
      },
      "Radius": 1.3893172196846955,
      "StartAngle": 1.7144832674425987,
      "EndAngle": 4.5687020397369871,
      "Layer": "E-SYM1"
    },
    {
      "Center": {
        "X": -0.771436168177388,
        "Y": -1.3749999999993179,
        "Z": 0.0
      },
      "Radius": 1.57662258057225,
      "StartAngle": 5.2236720806602133,
      "EndAngle": 1.0595132265193734,
      "Layer": "E-SYM1"
    },
    {
      "Center": {
        "X": -1.8189894035458565E-12,
        "Y": 6.8212102632969618E-13,
        "Z": 0.0
      },
      "Radius": 2.7500000000001137,
      "StartAngle": 4.7123889803919656,
      "EndAngle": 1.5707963267948966,
      "Layer": "E-SYM1"
    }
  ],
  "Circles": [
    {
      "Center": {
        "X": 0.0,
        "Y": 9.0949470177292824E-13,
        "Z": 0.0
      },
      "Radius": 2.75,
      "Layer": "E-SYM1"
    }
  ],
  "Ellipses": [],
  "MTexts": [],
  "Texts": [],
  "Solids": [],
  "Hatches": [
    {
      "Layer": "E-SYM1",
      "PatternName": "SOLID",
      "PatternScale": 1.0,
      "PatternType": 1,
      "Angle": 0.0,
      "Polylines": [],
      "Lines": [],
      "Arcs": [
        {
          "Center": {
            "X": -1.8189894035458565E-12,
            "Y": 6.8212102632969618E-13,
            "Z": 0.0
          },
          "Radius": 2.7500000000001137,
          "StartAngle": 4.712388980392193,
          "EndAngle": 7.8539816339744828,
          "Layer": "E-SYM1"
        },
        {
          "Center": {
            "X": 0.19894053612006246,
            "Y": 1.3750000000006821,
            "Z": 0.0
          },
          "Radius": 1.3893172196846955,
          "StartAngle": 1.714483267443691,
          "EndAngle": 4.5687020397358955,
          "Layer": "E-SYM1"
        },
        {
          "Center": {
            "X": -0.771436168177388,
            "Y": -1.3749999999993179,
            "Z": 0.0
          },
          "Radius": 1.57662258057225,
          "StartAngle": 5.2236720806594192,
          "EndAngle": 7.3426985336997532,
          "Layer": "E-SYM1"
        }
      ],
      "Circles": [],
      "Ellipses": [],
      "Splines": []
    }
  ],
  "Splines": [],
  "AttributeDefinitions": [],
  "NumberOfRows": 0,
  "Scale": 0.25
}